pandex/__init__.py
pandex/_build_info.py
pandex/_version.py
pandex/symbols.py
pandex/extensions/__init__.py
pandex/extensions/collection.py
pandex/extensions/extension.py
pandex/extensions/extension_importer.py
pandex/extensions/extension_info.py
pandex/extensions/register_extensions.py
pandex/installed_extensions/README
pandex/installed_extensions/locations.yml
pandex/repository/ExtensionRepository.py
pandex/repository/__init__.py
pandex/repository/config_file_management.py
pandex/repository/extension_location.py
pandex/repository/extension_management.py
pandex/repository/extension_properties.py
pandex/repository/extension_spec.py
pandex/repository/user_extension_control_methods.py
pandex/repository/user_extension_install_methods.py
pandex/repository/user_repository_methods.py
pandex-0.2.1.dist-info/LICENSE
pandex-0.2.1.dist-info/METADATA
pandex-0.2.1.dist-info/WHEEL
pandex-0.2.1.dist-info/top_level.txt
pandex-0.2.1.dist-info/RECORD
