Metadata-Version: 2.1
Name: pandex
Version: 0.2.1
Summary: Extension framework for pandas
Home-page: http://github.com/connectedblue/pdext
Author: Chris Shaw
Author-email: chris@connectedblue.com
License: UNKNOWN
Keywords: pandas,extensions
Platform: UNKNOWN
Classifier: Programming Language :: Python :: 3
Classifier: License :: OSI Approved :: GNU General Public License v3 (GPLv3)
Classifier: Operating System :: OS Independent
Classifier: Development Status :: 4 - Beta
Classifier: Natural Language :: English
Classifier: Environment :: Console
Classifier: Intended Audience :: Science/Research
Classifier: Topic :: Scientific/Engineering
Classifier: Topic :: Software Development :: Libraries
Requires-Python: >=3
Requires-Dist: pandas
Requires-Dist: pyyaml
